odoo/addons/beesdoo_product/README.rst
odoo/addons/beesdoo_product/__init__.py
odoo/addons/beesdoo_product/__manifest__.py
odoo/addons/beesdoo_product/data/barcode_rule.xml
odoo/addons/beesdoo_product/data/product_hazard.xml
odoo/addons/beesdoo_product/data/product_label.xml
odoo/addons/beesdoo_product/data/product_sequence.xml
odoo/addons/beesdoo_product/i18n/fr_BE.po
odoo/addons/beesdoo_product/models/__init__.py
odoo/addons/beesdoo_product/models/beesdoo_product.py
odoo/addons/beesdoo_product/models/res_config_settings.py
odoo/addons/beesdoo_product/readme/CONTRIBUTORS.rst
odoo/addons/beesdoo_product/readme/DESCRIPTION.rst
odoo/addons/beesdoo_product/security/ir.model.access.csv
odoo/addons/beesdoo_product/static/description/index.html
odoo/addons/beesdoo_product/static/src/js/models.js
odoo/addons/beesdoo_product/tests/__init__.py
odoo/addons/beesdoo_product/tests/test_suggested_price.py
odoo/addons/beesdoo_product/views/assets.xml
odoo/addons/beesdoo_product/views/beesdoo_product.xml
odoo/addons/beesdoo_product/views/point_of_sale_view.xml
odoo/addons/beesdoo_product/views/purchase_views.xml
odoo/addons/beesdoo_product/views/res_config_settings.xml
odoo/addons/beesdoo_product/views/sale_views.xml
odoo/addons/beesdoo_product/wizard/__init__.py
odoo/addons/beesdoo_product/wizard/adapt_sales_price_wizard.py
odoo/addons/beesdoo_product/wizard/label_printing_utils.py
odoo/addons/beesdoo_product/wizard/views/adapt_sales_price_wizard_view.xml
odoo/addons/beesdoo_product/wizard/views/label_printing_utils.xml
odoo12_addon_beesdoo_product-12.0.1.2.0.dist-info/METADATA
odoo12_addon_beesdoo_product-12.0.1.2.0.dist-info/WHEEL
odoo12_addon_beesdoo_product-12.0.1.2.0.dist-info/top_level.txt
odoo12_addon_beesdoo_product-12.0.1.2.0.dist-info/RECORD
