Metadata-Version: 2.1
Name: odoo12-addon-beesdoo-product
Version: 12.0.1.2.0
Summary: Modification of product module for the needs of beescoop
Home-page: https://github.com/beescoop/Obeesdoo
Author: Beescoop - Cellule IT, Coop IT Easy SCRLfs
License: AGPL-3
Platform: UNKNOWN
Classifier: Programming Language :: Python
Classifier: Framework :: Odoo
Classifier: Framework :: Odoo :: 12.0
Classifier: License :: OSI Approved :: GNU Affero General Public License v3
Requires-Python: >=3.5
Requires-Dist: odoo12-addon-beesdoo-base
Requires-Dist: odoo (<12.1dev,>=12.0a)
